human_readable_ids/__init__.py
human_readable_ids/adjectives.py
human_readable_ids/nouns.py
human_readable_ids/random_word.py
human_readable_ids-0.1.3.dist-info/WHEEL
human_readable_ids-0.1.3.dist-info/METADATA
human_readable_ids-0.1.3.dist-info/RECORD
