Metadata-Version: 2.1
Name: human-readable-ids
Version: 0.1.3
Summary: Generates a human readable ID using a format of: Adjective Noun ID
Home-page: https://github.com/JonnyFb421/human-readable-ids
Author: Jonny Carlyon
Author-email: jonathoncarlyon@gmail.com
Requires-Python: >=3.8,<4.0
Classifier: Programming Language :: Python :: 3
Classifier: Programming Language :: Python :: 3.8
Project-URL: Repository, https://github.com/JonnyFb421/human-readable-ids
